{
  "resourceType": "Bundle",
  "id": "9ab43a90-99be-4c2a-80bd-7e331d93074f",
  "meta": {
    "versionId": "1",
    "lastUpdated": "2025-10-13T11:17:55.458-03:00",
    "tag": [
      {
        "system": "message",
        "code": "response"
      }
    ]
  },
  "type": "message",
  "entry": [
    {
      "resource": {
        "resourceType": "MessageHeader",
        "id": "e3d47bd3-1cec-4474-9761-cb7a503ad7a9",
        "meta": {
          "lastUpdated": "2025-10-05T17:01:03.604+00:00",
          "profile": [
            "https://interoperabilidad.minsal.cl/fhir/ig/tei/StructureDefinition/MessageHeaderLE"
          ]
        },
        "eventCoding": {
          "system": "https://interoperabilidad.minsal.cl/fhir/ig/tei/CodeSystem/CSTipoEventoLE",
          "code": "terminar",
          "display": "Terminar"
        },
        "author": {
          "reference": "PractitionerRole/6fe921d1-20e8-45a7-9d31-805355928be6"
        },
        "source": {
          "software": "rayen-cesfam-lopetegui",
          "endpoint": "rayen.cesfam-lopetegui.cl"
        },
        "focus": [
          {
            "reference": "ServiceRequest/413bff47-0f6d-4eda-bfac-ae0a376cd296"
          }
        ]
      },
      "request": {
        "method": "PUT",
        "url": "MessageHeader/e3d47bd3-1cec-4474-9761-cb7a503ad7a9"
      }
    },
    {
      "resource": {
        "resourceType": "MessageHeader",
        "id": "e3d47bd3-1cec-4474-9761-cb7a503ad7a9",
        "meta": {
          "versionId": "1",
          "lastUpdated": "2025-10-13T14:17:55.303+00:00",
          "profile": [
            "https://interoperabilidad.minsal.cl/fhir/ig/tei/StructureDefinition/MessageHeaderLE"
          ]
        },
        "eventCoding": {
          "system": "https://interoperabilidad.minsal.cl/fhir/ig/tei/CodeSystem/CSTipoEventoLE",
          "code": "terminar",
          "display": "Terminar"
        },
        "author": {
          "reference": "PractitionerRole/6fe921d1-20e8-45a7-9d31-805355928be6"
        },
        "source": {
          "software": "rayen-cesfam-lopetegui",
          "endpoint": "rayen.cesfam-lopetegui.cl"
        },
        "focus": [
          {
            "reference": "ServiceRequest/413bff47-0f6d-4eda-bfac-ae0a376cd296"
          }
        ]
      },
      "response": {
        "id": "e3d47bd3-1cec-4474-9761-cb7a503ad7a9",
        "status": "201 Created",
        "location": "MessageHeader/e3d47bd3-1cec-4474-9761-cb7a503ad7a9/_history/1",
        "lastModified": "2025-10-13T11:17:55.303-03:00"
      }
    },
    {
      "resource": {
        "resourceType": "ServiceRequest",
        "id": "413bff47-0f6d-4eda-bfac-ae0a376cd296",
        "meta": {
          "versionId": "3",
          "lastUpdated": "2025-10-13T11:17:55.409-03:00",
          "profile": [
            "https://interoperabilidad.minsal.cl/fhir/ig/tei/StructureDefinition/ServiceRequestLE"
          ]
        },
        "extension": [
          {
            "url": "https://interoperabilidad.minsal.cl/fhir/ig/tei/StructureDefinition/ExtensionEstadoInterconsultaCodigoLE",
            "valueCodeableConcept": {
              "coding": [
                {
                  "system": "https://interoperabilidad.minsal.cl/fhir/ig/tei/CodeSystem/CSEstadoInterconsulta",
                  "code": "7",
                  "display": "Cerrada"
                }
              ]
            }
          },
          {
            "url": "https://interoperabilidad.minsal.cl/fhir/ig/tei/StructureDefinition/ExtensionMotivoCierreInterconsulta",
            "valueCodeableConcept": {
              "coding": [
                {
                  "system": "https://interoperabilidad.minsal.cl/fhir/ig/tei/CodeSystem/CSMotivoCierreInterconsulta",
                  "code": "18",
                  "display": "Atención hospital digital (19)"
                }
              ]
            }
          }
        ],
        "identifier": [
          {
            "value": "a4cdd9f0-625e-4801-9c3f-34c38d161f9b"
          }
        ],
        "status": "draft",
        "intent": "order",
        "category": [
          {
            "coding": [
              {
                "system": "https://interoperabilidad.minsal.cl/fhir/ig/tei/CodeSystem/CSModalidadAtencionCodigo",
                "code": "3",
                "display": "Telemedicina"
              }
            ]
          }
        ],
        "subject": {
          "reference": "Patient/AC1759438544804"
        },
        "authoredOn": "2025-09-05T00:00:00+00:00",
        "performer": [
          {
            "reference": "PractitionerRole/0e68d9d2-e643-4529-93ff-aaaa77852149"
          }
        ]
      },
      "response": {
        "id": "413bff47-0f6d-4eda-bfac-ae0a376cd296",
        "status": "200 OK",
        "location": "ServiceRequest/413bff47-0f6d-4eda-bfac-ae0a376cd296/_history/3",
        "lastModified": "2025-10-13T11:17:55.409-03:00"
      }
    },
    {
      "resource": {
        "resourceType": "Practitioner",
        "id": "dec38b0d-0f9d-41c1-b057-6d94995d9445",
        "meta": {
          "versionId": "1",
          "lastUpdated": "2025-10-13T14:17:55.432+00:00",
          "profile": [
            "https://interoperabilidad.minsal.cl/fhir/ig/tei/StructureDefinition/PractitionerProfesionalLE"
          ]
        },
        "extension": [
          {
            "url": "https://hl7chile.cl/fhir/ig/clcore/StructureDefinition/CodigoPaises",
            "valueCodeableConcept": {
              "coding": [
                {
                  "system": "https://hl7chile.cl/fhir/ig/clcore/CodeSystem/CodPais",
                  "code": "152",
                  "display": "Chile"
                }
              ]
            }
          }
        ],
        "identifier": [
          {
            "use": "official",
            "type": {
              "coding": [
                {
                  "system": "https://hl7chile.cl/fhir/ig/clcore/CodeSystem/CSTipoIdentificador",
                  "code": "01",
                  "display": "RUN"
                }
              ],
              "text": "RUN"
            },
            "value": "889900"
          },
          {
            "use": "official",
            "type": {
              "coding": [
                {
                  "system": "https://hl7chile.cl/fhir/ig/clcore/CodeSystem/CSTipoIdentificador",
                  "code": "13",
                  "display": "RNPI"
                }
              ],
              "text": "RNPI"
            },
            "value": "889900"
          }
        ],
        "active": true,
        "name": [
          {
            "use": "official",
            "family": "Molina",
            "_family": {
              "extension": [
                {
                  "url": "https://hl7chile.cl/fhir/ig/clcore/StructureDefinition/SegundoApellido",
                  "valueString": "Reyes"
                }
              ]
            },
            "given": [
              "Javier"
            ]
          }
        ],
        "telecom": [
          {
            "system": "email",
            "value": "javier.molina@hospitaldigital.cl"
          }
        ],
        "gender": "male",
        "birthDate": "1979-06-05",
        "qualification": [
          {
            "identifier": [
              {
                "value": "cert"
              }
            ],
            "code": {
              "coding": [
                {
                  "system": "https://interoperabilidad.minsal.cl/fhir/ig/tei/CodeSystem/CSTituloProfesional",
                  "code": "1",
                  "display": "MÉDICO CIRUJANO"
                }
              ],
              "text": "MÉDICO CIRUJANO"
            },
            "period": {
              "start": "2005-12-10T00:00:00+00:00"
            },
            "issuer": {
              "display": "Universidad de Chile"
            }
          },
          {
            "identifier": [
              {
                "value": "esp"
              }
            ],
            "code": {
              "coding": [
                {
                  "system": "https://interoperabilidad.minsal.cl/fhir/ig/tei/CodeSystem/CSEspecialidadMed",
                  "code": "34",
                  "display": "TRAUMATOLOGÍA"
                }
              ],
              "text": "TRAUMATOLOGÍA"
            },
            "period": {
              "start": "2010-04-18T00:00:00+00:00"
            },
            "issuer": {
              "display": "Colegio Médico de Chile"
            }
          }
        ]
      },
      "response": {
        "id": "dec38b0d-0f9d-41c1-b057-6d94995d9445",
        "status": "201 Created",
        "location": "Practitioner/dec38b0d-0f9d-41c1-b057-6d94995d9445/_history/1",
        "lastModified": "2025-10-13T11:17:55.432-03:00"
      }
    },
    {
      "resource": {
        "resourceType": "PractitionerRole",
        "id": "6fe921d1-20e8-45a7-9d31-805355928be6",
        "meta": {
          "versionId": "1",
          "lastUpdated": "2025-10-13T11:17:55.447-03:00",
          "profile": [
            "https://interoperabilidad.minsal.cl/fhir/ig/tei/StructureDefinition/PractitionerRoleLE"
          ]
        },
        "practitioner": {
          "reference": "Practitioner/dec38b0d-0f9d-41c1-b057-6d94995d9445"
        },
        "organization": {
          "reference": "Organization/1d40cd55-e1ab-421b-86f0-e8d53f876299"
        },
        "code": [
          {
            "coding": [
              {
                "system": "https://interoperabilidad.minsal.cl/fhir/ig/tei/CodeSystem/CSPractitionerTipoRolLE",
                "code": "terminador",
                "display": "Terminador"
              }
            ],
            "text": "terminador"
          }
        ]
      },
      "response": {
        "id": "6fe921d1-20e8-45a7-9d31-805355928be6",
        "status": "201 Created",
        "location": "PractitionerRole/6fe921d1-20e8-45a7-9d31-805355928be6/_history/1",
        "lastModified": "2025-10-13T11:17:55.447-03:00"
      }
    },
    {
      "resource": {
        "resourceType": "Organization",
        "id": "1d40cd55-e1ab-421b-86f0-e8d53f876299",
        "meta": {
          "versionId": "1",
          "lastUpdated": "2025-10-13T11:17:55.394-03:00",
          "profile": [
            "https://interoperabilidad.minsal.cl/fhir/ig/tei/StructureDefinition/OrganizationLE"
          ]
        },
        "identifier": [
          {
            "system": "https://interoperabilidad.minsal.cl/fhir/ig/tei/CodeSystem/CSEstablecimientoDestino",
            "value": "123301"
          }
        ],
        "name": "CESFAM Dr. Marcelo Lopetegui"
      },
      "response": {
        "id": "1d40cd55-e1ab-421b-86f0-e8d53f876299",
        "status": "201 Created",
        "location": "Organization/1d40cd55-e1ab-421b-86f0-e8d53f876299/_history/1",
        "lastModified": "2025-10-13T11:17:55.394-03:00"
      }
    }
  ]
}